{
    "Ar36": {
        "error": 9.516391502768636e-09,
        "error_type": "",
        "fit": "previous",
        "references": [
            {
                "exclude": false,
                "record_id": "ba-01-n-16943"
            }
        ],
        "value": 3.763855992019101e-07
    },
    "Ar37": {
        "error": 2.0315057079220635e-07,
        "error_type": "",
        "fit": "previous",
        "references": [
            {
                "exclude": false,
                "record_id": "ba-01-n-16943"
            }
        ],
        "value": 8.558803109526e-07
    },
    "Ar38": {
        "error": 3.0671051638376775e-07,
        "error_type": "",
        "fit": "previous",
        "references": [
            {
                "exclude": false,
                "record_id": "ba-01-n-16943"
            }
        ],
        "value": 2.3766638400422955e-07
    },
    "Ar39": {
        "error": 3.430324810472459e-07,
        "error_type": "",
        "fit": "previous",
        "references": [
            {
                "exclude": false,
                "record_id": "ba-01-n-16943"
            }
        ],
        "value": 9.920468106749177e-07
    },
    "Ar40": {
        "error": 9.664659954324992e-07,
        "error_type": "",
        "fit": "previous",
        "references": [
            {
                "exclude": false,
                "record_id": "ba-01-n-16943"
            }
        ],
        "value": 7.581208707980048e-05
    }
}